{"objects":{"components":[{"uuid":"a7417ef6-2e6c-4b81-a4ce-154e47224f45-00025ecf","name":"常规 - 200mm 2","familyName":"楼板","typeName":"常规 - 200mm 2","typeId":155355,"revitId":"155343","type":"Floor","category":"OST_Floors","properties":{"Category":"楼板","Name":"常规 - 200mm 2","ElementPoint":null,"ElementRotation":null,"Mirrored":null,"HandFlipped":null,"HandOrientation":null,"FacingFlipped":null,"FacingOrientation":null,"Translation":null,"matrix":null,"BoundingBox":"(0.146900684, 0.734254663, 0.656167979),(-4.774359159, -4.187005179, 0.000000000)","标高":"展示层面","自标高的高度偏移":"200","结构":"是","图像":"<无>","创建的阶段":"阶段 1","拆除的阶段":"无","启用分析模型":"是","钢筋保护层 - 顶面":"钢筋保护层 1 <25 mm>","钢筋保护层 - 底面":"钢筋保护层 1 <25 mm>","钢筋保护层 - 其他面":"钢筋保护层 1 <25 mm>","坡度":"0.00°","房间边界":"是","周长":"6000","面积":"2 m²","体积":"0.45 m³","与体量相关":"否","顶部高程":"200","底部高程":"0","厚度":"200","默认的厚度":"200","类型图像":"<无>","结构材质":"混凝土 - 现场浇注","成本":"0.00","功能":"内部","传热系数(U)":"0.0000 W/(m²·K)","热阻(R)":"0.0000 (m²·K)/W","热质量":"0.00 kJ/K","吸收率":"0.7","粗糙度":"3"}},{"uuid":"a7417ef6-2e6c-4b81-a4ce-154e47224f45-00025f30","name":"常规 - 40mm 3","familyName":"楼板","typeName":"常规 - 40mm 3","typeId":155468,"revitId":"155440","type":"Floor","category":"OST_Floors","properties":{"Category":"楼板","Name":"常规 - 40mm 3","ElementPoint":null,"ElementRotation":null,"Mirrored":null,"HandFlipped":null,"HandOrientation":null,"FacingFlipped":null,"FacingOrientation":null,"Translation":null,"matrix":null,"BoundingBox":"(-0.181183306, 0.406170674, 0.787401575),(-4.774359159, -4.187005179, 0.656167979)","标高":"结构板顶","自标高的高度偏移":"40","结构":"否","图像":"<无>","创建的阶段":"阶段 1","拆除的阶段":"无","启用分析模型":"否","坡度":"0.00°","房间边界":"是","周长":"5426","面积":"2 m²","体积":"0.08 m³","与体量相关":"否","顶部高程":"240","底部高程":"200","厚度":"40","默认的厚度":"40","类型图像":"<无>","结构材质":"混凝土，预制","成本":"0.00","功能":"内部","传热系数(U)":"26.1500 W/(m²·K)","热阻(R)":"0.0382 (m²·K)/W","热质量":"5.62 kJ/K","吸收率":"0.7","粗糙度":"3"}},{"uuid":"a7417ef6-2e6c-4b81-a4ce-154e47224f45-00025f87","name":"常规 - 2mm 4","familyName":"楼板","typeName":"常规 - 2mm 4","typeId":155700,"revitId":"155527","type":"Floor","category":"OST_Floors","properties":{"Category":"楼板","Name":"常规 - 2mm 4","ElementPoint":null,"ElementRotation":null,"Mirrored":null,"HandFlipped":null,"HandOrientation":null,"FacingFlipped":null,"FacingOrientation":null,"Translation":null,"matrix":null,"BoundingBox":"(-0.181183306, 0.406170674, 0.793963255),(-4.774359159, -4.187005179, 0.787401575)","标高":"发泡顶","自标高的高度偏移":"2","结构":"否","图像":"<无>","创建的阶段":"阶段 1","拆除的阶段":"无","启用分析模型":"否","坡度":"0.00°","房间边界":"是","周长":"5294","面积":"2 m²","体积":"0.00 m³","与体量相关":"否","顶部高程":"242","底部高程":"240","厚度":"2","默认的厚度":"2","类型图像":"<无>","结构材质":"聚氨酯泡沫","类型标记":"发泡","成本":"0.00","功能":"内部","传热系数(U)":"16.0000 W/(m²·K)","热阻(R)":"0.0625 (m²·K)/W","热质量":"0.01 kJ/K","吸收率":"0.7","粗糙度":"3"}},{"uuid":"d265ea86-6a90-403a-ad9c-e7a873a33776-00026073","name":"常规 - 20mm 5","familyName":"楼板","typeName":"常规 - 20mm 5","typeId":155765,"revitId":"155763","type":"Floor","category":"OST_Floors","properties":{"Category":"楼板","Name":"常规 - 20mm 5","ElementPoint":null,"ElementRotation":null,"Mirrored":null,"HandFlipped":null,"HandOrientation":null,"FacingFlipped":null,"FacingOrientation":null,"Translation":null,"matrix":null,"BoundingBox":"(-0.181183306, 0.406170674, 0.859580052),(-4.774359159, -4.187005179, 0.793963255)","标高":"聚氨酯顶","自标高的高度偏移":"20","结构":"否","图像":"<无>","创建的阶段":"阶段 1","拆除的阶段":"无","启用分析模型":"否","坡度":"0.00°","房间边界":"是","周长":"5161","面积":"2 m²","体积":"0.03 m³","与体量相关":"否","顶部高程":"262","底部高程":"242","厚度":"20","默认的厚度":"20","类型图像":"<无>","结构材质":"混凝土 - 沙/水泥找平","类型标记":"聚氨酯防水","成本":"0.00","功能":"内部","传热系数(U)":"0.0000 W/(m²·K)","热阻(R)":"0.0000 (m²·K)/W","热质量":"0.00 kJ/K","吸收率":"0.7","粗糙度":"3"}},{"uuid":"d265ea86-6a90-403a-ad9c-e7a873a33776-00026172","name":"常规 - 50mm 6","familyName":"楼板","typeName":"常规 - 50mm 6","typeId":156160,"revitId":"156018","type":"Floor","category":"OST_Floors","properties":{"Category":"楼板","Name":"常规 - 50mm 6","ElementPoint":null,"ElementRotation":null,"Mirrored":null,"HandFlipped":null,"HandOrientation":null,"FacingFlipped":null,"FacingOrientation":null,"Translation":null,"matrix":null,"BoundingBox":"(-0.181183306, 0.406170674, 1.023622047),(-4.774359159, -4.187005179, 0.859580052)","标高":"水泥砂浆顶","自标高的高度偏移":"50","结构":"否","图像":"<无>","创建的阶段":"阶段 1","拆除的阶段":"无","启用分析模型":"否","坡度":"0.00°","房间边界":"是","周长":"5304","面积":"1 m²","体积":"0.07 m³","与体量相关":"否","顶部高程":"312","底部高程":"262","厚度":"50","默认的厚度":"50","类型图像":"<无>","结构材质":"灰泥","类型标记":"水泥砂浆","成本":"0.00","功能":"内部","传热系数(U)":"14.4000 W/(m²·K)","热阻(R)":"0.0694 (m²·K)/W","热质量":"7.26 kJ/K","吸收率":"0.7","粗糙度":"3"}},{"uuid":"d265ea86-6a90-403a-ad9c-e7a873a33776-000263fc","name":"常规 - 225mm 砌体","familyName":"基本墙","typeName":"常规 - 225mm 砌体","typeId":1741,"revitId":"156668","type":"Wall","category":"OST_Walls","properties":{"Category":"墙","Name":"常规 - 225mm 砌体","ElementPoint":null,"ElementRotation":null,"Mirrored":null,"HandFlipped":null,"HandOrientation":null,"FacingFlipped":null,"FacingOrientation":null,"Translation":null,"matrix":null,"BoundingBox":"(-0.017141311, 0.734254663, 1.640419948),(-4.777639999, 0.406170674, 0.656167979)","结构":"是","启用分析模型":"是","结构用途":"承重","定位线":"面层面: 外部","图像":"<无>","创建的阶段":"阶段 1","拆除的阶段":"无","钢筋保护层 - 外部面":"钢筋保护层 1 <25 mm>","钢筋保护层 - 内部面":"钢筋保护层 1 <25 mm>","钢筋保护层 - 其他面":"钢筋保护层 1 <25 mm>","底部约束":"展示层面","底部偏移":"200","已附着底部":"否","底部延伸距离":"0","顶部约束":"未连接","无连接高度":"300","顶部偏移":"0","已附着顶部":"否","顶部延伸距离":"0","房间边界":"是","长度":"1451","面积":"0 m²","体积":"0.04 m³","与体量相关":"否","粗略比例填充样式":"交叉线 3mm","在插入点包络":"不包络","在端点包络":"无","厚度":"100","类型图像":"<无>","结构材质":"混凝土 - 现场浇注","成本":"0.00","功能":"外部","壁厚":"0","幕墙":"否","传热系数(U)":"0.0000 W/(m²·K)","热阻(R)":"0.0000 (m²·K)/W","热质量":"0.00 kJ/K","吸收率":"0.7","粗糙度":"3"}},{"uuid":"d265ea86-6a90-403a-ad9c-e7a873a33776-0002643f","name":"常规 - 225mm 砌体","familyName":"基本墙","typeName":"常规 - 225mm 砌体","typeId":1741,"revitId":"156735","type":"Wall","category":"OST_Walls","properties":{"Category":"墙","Name":"常规 - 225mm 砌体","ElementPoint":null,"ElementRotation":null,"Mirrored":null,"HandFlipped":null,"HandOrientation":null,"FacingFlipped":null,"FacingOrientation":null,"Translation":null,"matrix":null,"BoundingBox":"(0.146900684, 0.734254663, 1.640419948),(-0.181183306, -4.187005179, 0.656167979)","结构":"是","启用分析模型":"是","结构用途":"承重","定位线":"面层面: 外部","图像":"<无>","创建的阶段":"阶段 1","拆除的阶段":"无","钢筋保护层 - 外部面":"钢筋保护层 1 <25 mm>","钢筋保护层 - 内部面":"钢筋保护层 1 <25 mm>","钢筋保护层 - 其他面":"钢筋保护层 1 <25 mm>","底部约束":"展示层面","底部偏移":"200","已附着底部":"否","底部延伸距离":"0","顶部约束":"未连接","无连接高度":"300","顶部偏移":"0","已附着顶部":"否","顶部延伸距离":"0","房间边界":"是","长度":"1450","面积":"0 m²","体积":"0.05 m³","与体量相关":"否","粗略比例填充样式":"交叉线 3mm","在插入点包络":"不包络","在端点包络":"无","厚度":"100","类型图像":"<无>","结构材质":"混凝土 - 现场浇注","成本":"0.00","功能":"外部","壁厚":"0","幕墙":"否","传热系数(U)":"0.0000 W/(m²·K)","热阻(R)":"0.0000 (m²·K)/W","热质量":"0.00 kJ/K","吸收率":"0.7","粗糙度":"3"}},{"uuid":"827ce9b4-bc8d-417e-9262-ab4b400b4f59-00026853","name":"常规 - 225mm 砌体 2","familyName":"基本墙","typeName":"常规 - 225mm 砌体 2","typeId":157727,"revitId":"157779","type":"Wall","category":"OST_Walls","properties":{"Category":"墙","Name":"常规 - 225mm 砌体 2","ElementPoint":null,"ElementRotation":null,"Mirrored":null,"HandFlipped":null,"HandOrientation":null,"FacingFlipped":null,"FacingOrientation":null,"Translation":null,"matrix":null,"BoundingBox":"(-0.017141311, 0.734254663, 4.810021442),(-4.777639999, 0.406170674, 1.640419948)","结构":"否","启用分析模型":"否","结构用途":"非承重","定位线":"面层面: 外部","图像":"<无>","创建的阶段":"阶段 1","拆除的阶段":"无","底部约束":"标高 12","底部偏移":"0","已附着底部":"否","底部延伸距离":"0","顶部约束":"未连接","无连接高度":"966","顶部偏移":"0","已附着顶部":"否","顶部延伸距离":"0","房间边界":"是","长度":"1451","面积":"1 m²","体积":"0.14 m³","与体量相关":"否","粗略比例填充样式":"交叉线 3mm","在插入点包络":"不包络","在端点包络":"无","厚度":"100","类型图像":"<无>","结构材质":"混凝土砌块(2)","成本":"0.00","功能":"外部","壁厚":"0","幕墙":"否","传热系数(U)":"13.0000 W/(m²·K)","热阻(R)":"0.0769 (m²·K)/W","热质量":"14.05 kJ/K","吸收率":"0.7","粗糙度":"3"}},{"uuid":"827ce9b4-bc8d-417e-9262-ab4b400b4f59-00026877","name":"常规 - 225mm 砌体 2","familyName":"基本墙","typeName":"常规 - 225mm 砌体 2","typeId":157727,"revitId":"157815","type":"Wall","category":"OST_Walls","properties":{"Category":"墙","Name":"常规 - 225mm 砌体 2","ElementPoint":null,"ElementRotation":null,"Mirrored":null,"HandFlipped":null,"HandOrientation":null,"FacingFlipped":null,"FacingOrientation":null,"Translation":null,"matrix":null,"BoundingBox":"(0.146900684, 0.734254663, 4.810021442),(-0.181183306, -4.187005179, 1.640419948)","结构":"否","启用分析模型":"否","结构用途":"非承重","定位线":"面层面: 外部","图像":"<无>","创建的阶段":"阶段 1","拆除的阶段":"无","底部约束":"标高 12","底部偏移":"0","已附着底部":"否","底部延伸距离":"0","顶部约束":"未连接","无连接高度":"966","顶部偏移":"0","已附着顶部":"否","顶部延伸距离":"0","房间边界":"是","长度":"1450","面积":"1 m²","体积":"0.14 m³","与体量相关":"否","粗略比例填充样式":"交叉线 3mm","在插入点包络":"不包络","在端点包络":"无","厚度":"100","类型图像":"<无>","结构材质":"混凝土砌块(2)","成本":"0.00","功能":"外部","壁厚":"0","幕墙":"否","传热系数(U)":"13.0000 W/(m²·K)","热阻(R)":"0.0769 (m²·K)/W","热质量":"14.05 kJ/K","吸收率":"0.7","粗糙度":"3"}},{"uuid":"cb0db32e-19e2-45c6-aa2f-bc55add5ec6f-00027b0a","name":"内部 - 79mm 隔断(1-hr)","familyName":"基本墙","typeName":"内部 - 79mm 隔断(1-hr)","typeId":1744,"revitId":"162570","type":"Wall","category":"OST_Walls","properties":{"Category":"墙","Name":"内部 - 79mm 隔断(1-hr)","ElementPoint":null,"ElementRotation":null,"Mirrored":null,"HandFlipped":null,"HandOrientation":null,"FacingFlipped":null,"FacingOrientation":null,"Translation":null,"matrix":null,"BoundingBox":"(-1.493519264, 0.570212668, 4.810021442),(-1.713335537, -1.125981557, 0.984251969)","结构":"否","启用分析模型":"否","结构用途":"非承重","定位线":"墙中心线","图像":"<无>","创建的阶段":"阶段 1","拆除的阶段":"无","底部约束":"展示层面","底部偏移":"300","已附着底部":"否","底部延伸距离":"0","顶部约束":"未连接","无连接高度":"1166","顶部偏移":"0","已附着顶部":"否","顶部延伸距离":"0","房间边界":"是","长度":"484","面积":"1 m²","体积":"0.04 m³","与体量相关":"否","在插入点包络":"不包络","在端点包络":"无","厚度":"67","类型图像":"<无>","结构材质":"不锈钢","成本":"0.00","功能":"内部","壁厚":"0","幕墙":"否","传热系数(U)":"385.7143 W/(m²·K)","热阻(R)":"0.0026 (m²·K)/W","热质量":"15.61 kJ/K","吸收率":"0.7","粗糙度":"3"}},{"uuid":"cb0db32e-19e2-45c6-aa2f-bc55add5ec6f-00027b36","name":"内部 - 79mm 隔断(1-hr)","familyName":"基本墙","typeName":"内部 - 79mm 隔断(1-hr)","typeId":1744,"revitId":"162614","type":"Wall","category":"OST_Walls","properties":{"Category":"墙","Name":"内部 - 79mm 隔断(1-hr)","ElementPoint":null,"ElementRotation":null,"Mirrored":null,"HandFlipped":null,"HandOrientation":null,"FacingFlipped":null,"FacingOrientation":null,"Translation":null,"matrix":null,"BoundingBox":"(-0.017141311, -0.906165284, 4.810021442),(-1.603427400, -1.125981557, 0.984251969)","结构":"否","启用分析模型":"否","结构用途":"非承重","定位线":"墙中心线","图像":"<无>","创建的阶段":"阶段 1","拆除的阶段":"无","底部约束":"展示层面","底部偏移":"300","已附着底部":"否","底部延伸距离":"0","顶部约束":"未连接","无连接高度":"1166","顶部偏移":"0","已附着顶部":"否","顶部延伸距离":"0","房间边界":"是","长度":"484","面积":"0 m²","体积":"0.03 m³","与体量相关":"否","在插入点包络":"不包络","在端点包络":"无","厚度":"67","类型图像":"<无>","结构材质":"不锈钢","成本":"0.00","功能":"内部","壁厚":"0","幕墙":"否","传热系数(U)":"385.7143 W/(m²·K)","热阻(R)":"0.0026 (m²·K)/W","热质量":"15.61 kJ/K","吸收率":"0.7","粗糙度":"3"}},{"uuid":"b12e49b8-326c-4c85-982a-112e4bf5174b-0003a3dc","name":"PVC","familyName":"管道类型","typeName":"PVC","typeId":237677,"revitId":"238556","type":"Pipe","category":"OST_PipeCurves","properties":{"Category":"管道","Name":"PVC","ElementPoint":null,"ElementRotation":null,"Mirrored":null,"HandFlipped":null,"HandOrientation":null,"FacingFlipped":null,"FacingOrientation":null,"Translation":null,"matrix":null,"BoundingBox":"(-0.744615282, -1.451185811, 4.199475066),(-1.036281948, -1.742852477, 0.547408793)","系统分类":"其他","系统类型":"排水系统","系统名称":"排水系统 3","管段":"塑料 - Schedule 40","直径":"80 mm","连接类型":"常规","粗糙度":"0.774 mm","材质":"塑料","规格/类型":"Schedule 40","管内底标高":"167","剖面":"8","面积":"0 m²","相对粗糙度":"0.009935","图像":"<无>","总体大小":"80 mmø","隔热层厚度":"0 mm","外径":"89 mm","内径":"78 mm","尺寸":"80 mmø","标记":"28","创建的阶段":"阶段 1","拆除的阶段":"无","水平对正":"中心","垂直对正":"中","参照标高":"发泡顶","偏移":"-73","开始偏移":"-73","端点偏移":"1040","长度":"1113","坡度":"0.00%","类型图像":"<无>","成本":"0.00"}},{"uuid":"b12e49b8-326c-4c85-982a-112e4bf5174b-0003a3dd","name":"","familyName":"管道类型","typeName":"","typeId":-1,"revitId":"238557","type":"Element","category":"OST_PipeCurvesCenterLine","properties":{"Category":"中心线","Name":"","ElementPoint":null,"ElementRotation":null,"Mirrored":null,"HandFlipped":null,"HandOrientation":null,"FacingFlipped":null,"FacingOrientation":null,"Translation":null,"matrix":null,"BoundingBox":"(-0.890448615, -1.597019144, 4.199475066),(-0.890448615, -1.597019144, 0.547408793)","系统分类":"其他","系统类型":"排水系统","系统名称":"排水系统 3","管段":"塑料 - Schedule 40","直径":"80 mm","连接类型":"常规","粗糙度":"0.774 mm","材质":"塑料","规格/类型":"Schedule 40","管内底标高":"167","剖面":"0","面积":"0 m²","相对粗糙度":"0","图像":"<无>","总体大小":"80 mmø","隔热层厚度":"0 mm","外径":"89 mm","内径":"78 mm","尺寸":"80 mmø","标记":"28","创建的阶段":"阶段 1","拆除的阶段":"无","水平对正":"中心","垂直对正":"中","参照标高":"发泡顶","偏移":"-73","开始偏移":"-73","端点偏移":"1040","长度":"1113","坡度":"0.00%"}},{"uuid":"b12e49b8-326c-4c85-982a-112e4bf5174b-0003a5ec","name":"排水系统 2","familyName":"管道系统","typeName":"排水系统 2","typeId":238384,"revitId":"239084","type":"PipingSystem","category":"OST_PipingSystem","properties":{"Category":"管道系统","Name":"排水系统 2","ElementPoint":null,"ElementRotation":null,"Mirrored":null,"HandFlipped":null,"HandOrientation":null,"FacingFlipped":null,"FacingOrientation":null,"Translation":null,"matrix":null,"BoundingBox":"(0.467031700, -0.239538829, 2.643569554),(-2.247928930, -2.954499459, -0.773490814)","图像":"<无>","图元数":"0","系统名称":"排水系统 2","体积":"2.2 L","类型图像":"<无>","双线下降符号":"阴阳","双线上升符号":"轮廓","单线下降符号":"弯曲 - ¾ 圆","单线上升符号":"轮廓","单线 T 形三通向上符号":"轮廓","单线 T 形三通向下符号":"T 形三通 - 半圆","计算":"无","系统分类":"其他","材质":"<按类别>"}},{"uuid":"b12e49b8-326c-4c85-982a-112e4bf5174b-0003a60f","name":"PVC防水","familyName":"管道类型","typeName":"PVC防水","typeId":246139,"revitId":"239119","type":"Pipe","category":"OST_PipeCurves","properties":{"Category":"管道","Name":"PVC防水","ElementPoint":null,"ElementRotation":null,"Mirrored":null,"HandFlipped":null,"HandOrientation":null,"FacingFlipped":null,"FacingOrientation":null,"Translation":null,"matrix":null,"BoundingBox":"(-0.732968300, -1.439538829, 1.443569554),(-1.047928930, -1.754499459, 0.426509186)","系统分类":"其他","系统类型":"排水系统","系统名称":"排水系统 2","管段":"塑料 - Schedule 40","直径":"96 mm","连接类型":"常规","粗糙度":"0.774 mm","材质":"塑料","规格/类型":"Schedule 40","管内底标高":"130","剖面":"1","面积":"0 m²","相对粗糙度":"0.008065","图像":"<无>","总体大小":"96 mmø","隔热层厚度":"0 mm","外径":"96 mm","内径":"96 mm","尺寸":"96 mmø","标记":"31","创建的阶段":"阶段 1","拆除的阶段":"无","水平对正":"中心","垂直对正":"中","参照标高":"发泡顶","偏移":"-110","开始偏移":"-110","端点偏移":"200","长度":"310","坡度":"0.00%","类型图像":"<无>","成本":"0.00"}},{"uuid":"b12e49b8-326c-4c85-982a-112e4bf5174b-0003a610","name":"","familyName":"管道类型","typeName":"","typeId":-1,"revitId":"239120","type":"Element","category":"OST_PipeCurvesCenterLine","properties":{"Category":"中心线","Name":"","ElementPoint":null,"ElementRotation":null,"Mirrored":null,"HandFlipped":null,"HandOrientation":null,"FacingFlipped":null,"FacingOrientation":null,"Translation":null,"matrix":null,"BoundingBox":"(-0.890448615, -1.597019144, 1.443569554),(-0.890448615, -1.597019144, 0.426509186)","系统分类":"其他","系统类型":"排水系统","系统名称":"排水系统 2","管段":"塑料 - Schedule 40","直径":"96 mm","连接类型":"常规","粗糙度":"0.774 mm","材质":"塑料","规格/类型":"Schedule 40","管内底标高":"130","剖面":"0","面积":"0 m²","相对粗糙度":"0","图像":"<无>","总体大小":"96 mmø","隔热层厚度":"0 mm","外径":"96 mm","内径":"96 mm","尺寸":"96 mmø","标记":"31","创建的阶段":"阶段 1","拆除的阶段":"无","水平对正":"中心","垂直对正":"中","参照标高":"发泡顶","偏移":"-110","开始偏移":"-110","端点偏移":"200","长度":"310","坡度":"0.00%"}},{"uuid":"b12e49b8-326c-4c85-982a-112e4bf5174b-0003a79e","name":"PVC","familyName":"管道类型","typeName":"PVC","typeId":237677,"revitId":"239518","type":"Pipe","category":"OST_PipeCurves","properties":{"Category":"管道","Name":"PVC","ElementPoint":null,"ElementRotation":null,"Mirrored":null,"HandFlipped":null,"HandOrientation":null,"FacingFlipped":null,"FacingOrientation":null,"Translation":null,"matrix":null,"BoundingBox":"(-1.208198615, -1.451185811, 0.375492126),(-3.081937243, -1.742852477, 0.083825459)","系统分类":"其他","系统类型":"排水系统","系统名称":"排水系统 3","管段":"塑料 - Schedule 40","直径":"80 mm","连接类型":"常规","粗糙度":"0.774 mm","材质":"塑料","规格/类型":"Schedule 40","管内底标高":"31","剖面":"7","面积":"0 m²","相对粗糙度":"0.009935","图像":"<无>","总体大小":"80 mmø","隔热层厚度":"0 mm","外径":"89 mm","内径":"78 mm","尺寸":"80 mmø","标记":"32","创建的阶段":"阶段 1","拆除的阶段":"无","水平对正":"中心","垂直对正":"中","参照标高":"发泡顶","偏移":"-170","开始偏移":"-170","端点偏移":"-170","长度":"571","坡度":"0.00%","类型图像":"<无>","成本":"0.00"}},{"uuid":"b12e49b8-326c-4c85-982a-112e4bf5174b-0003a79f","name":"","familyName":"管道类型","typeName":"","typeId":-1,"revitId":"239519","type":"Element","category":"OST_PipeCurvesCenterLine","properties":{"Category":"中心线","Name":"","ElementPoint":null,"ElementRotation":null,"Mirrored":null,"HandFlipped":null,"HandOrientation":null,"FacingFlipped":null,"FacingOrientation":null,"Translation":null,"matrix":null,"BoundingBox":"(-1.208198615, -1.597019144, 0.229658793),(-3.081937243, -1.597019144, 0.229658793)","系统分类":"其他","系统类型":"排水系统","系统名称":"排水系统 3","管段":"塑料 - Schedule 40","直径":"80 mm","连接类型":"常规","粗糙度":"0.774 mm","材质":"塑料","规格/类型":"Schedule 40","管内底标高":"31","剖面":"0","面积":"0 m²","相对粗糙度":"0","图像":"<无>","总体大小":"80 mmø","隔热层厚度":"0 mm","外径":"89 mm","内径":"78 mm","尺寸":"80 mmø","标记":"32","创建的阶段":"阶段 1","拆除的阶段":"无","水平对正":"中心","垂直对正":"中","参照标高":"发泡顶","偏移":"-170","开始偏移":"-170","端点偏移":"-170","长度":"571","坡度":"0.00%"}},{"uuid":"b12e49b8-326c-4c85-982a-112e4bf5174b-0003a817","name":"卫生设备 1","familyName":"管道系统","typeName":"卫生设备 1","typeId":110198,"revitId":"239639","type":"PipingSystem","category":"OST_PipingSystem","properties":{"Category":"管道系统","Name":"卫生设备 1","ElementPoint":null,"ElementRotation":null,"Mirrored":null,"HandFlipped":null,"HandOrientation":null,"FacingFlipped":null,"FacingOrientation":null,"Translation":null,"matrix":null,"BoundingBox":"(-1.861760734, 1.504946011, 2.256430446),(-4.937613752, -2.079601329, -1.082341207)","图像":"<无>","图元数":"1","系统名称":"卫生设备 1","卫浴装置当量":"2","类型图像":"<无>","双线下降符号":"阴阳","双线上升符号":"轮廓","单线下降符号":"弯曲 - ¾ 圆","单线上升符号":"轮廓","单线 T 形三通向上符号":"轮廓","单线 T 形三通向下符号":"T 形三通 - 半圆","计算":"仅流量","系统分类":"卫生设备","材质":"<按类别>"}},{"uuid":"b12e49b8-326c-4c85-982a-112e4bf5174b-0003a822","name":"PVC","familyName":"管道类型","typeName":"PVC","typeId":237677,"revitId":"239650","type":"Pipe","category":"OST_PipeCurves","properties":{"Category":"管道","Name":"PVC","ElementPoint":null,"ElementRotation":null,"Mirrored":null,"HandFlipped":null,"HandOrientation":null,"FacingFlipped":null,"FacingOrientation":null,"Translation":null,"matrix":null,"BoundingBox":"(-3.300728909, 0.065977835, 0.482283465),(-3.498645576, -0.131938832, 0.440596293)","系统分类":"卫生设备","系统类型":"卫生设备","系统名称":"卫生设备 1","管段":"塑料 - Schedule 40","直径":"50 mm","连接类型":"常规","粗糙度":"0.774 mm","材质":"塑料","规格/类型":"Schedule 40","管内底标高":"134","剖面":"1","面积":"0 m²","相对粗糙度":"0.014746","图像":"<无>","总体大小":"50 mmø","隔热层厚度":"0 mm","卫浴装置当量":"2","外径":"60 mm","内径":"53 mm","尺寸":"50 mmø","标记":"35","创建的阶段":"阶段 1","拆除的阶段":"无","水平对正":"中心","垂直对正":"中","参照标高":"展示层面","偏移":"147","开始偏移":"147","端点偏移":"134","长度":"13","坡度":"0.00%","类型图像":"<无>","成本":"0.00"}},{"uuid":"b12e49b8-326c-4c85-982a-112e4bf5174b-0003a823","name":"","familyName":"管道类型","typeName":"","typeId":-1,"revitId":"239651","type":"Element","category":"OST_PipeCurvesCenterLine","properties":{"Category":"中心线","Name":"","ElementPoint":null,"ElementRotation":null,"Mirrored":null,"HandFlipped":null,"HandOrientation":null,"FacingFlipped":null,"FacingOrientation":null,"Translation":null,"matrix":null,"BoundingBox":"(-3.399687243, -0.032980498, 0.482283465),(-3.399687243, -0.032980498, 0.440596293)","系统分类":"卫生设备","系统类型":"卫生设备","系统名称":"卫生设备 1","管段":"塑料 - Schedule 40","直径":"50 mm","连接类型":"常规","粗糙度":"0.774 mm","材质":"塑料","规格/类型":"Schedule 40","管内底标高":"134","剖面":"0","面积":"0 m²","相对粗糙度":"0","图像":"<无>","总体大小":"50 mmø","隔热层厚度":"0 mm","卫浴装置当量":"2","外径":"60 mm","内径":"53 mm","尺寸":"50 mmø","标记":"35","创建的阶段":"阶段 1","拆除的阶段":"无","水平对正":"中心","垂直对正":"中","参照标高":"展示层面","偏移":"147","开始偏移":"147","端点偏移":"134","长度":"13","坡度":"0.00%"}},{"uuid":"b12e49b8-326c-4c85-982a-112e4bf5174b-0003a850","name":"PVC","familyName":"管道类型","typeName":"PVC","typeId":237677,"revitId":"239696","type":"Pipe","category":"OST_PipeCurves","properties":{"Category":"管道","Name":"PVC","ElementPoint":null,"ElementRotation":null,"Mirrored":null,"HandFlipped":null,"HandOrientation":null,"FacingFlipped":null,"FacingOrientation":null,"Translation":null,"matrix":null,"BoundingBox":"(-3.300728909, -0.243917998, 0.328617126),(-3.498645576, -0.879601329, 0.130700459)","系统分类":"卫生设备","系统类型":"卫生设备","系统名称":"卫生设备 1","管段":"塑料 - Schedule 40","直径":"50 mm","连接类型":"常规","粗糙度":"0.774 mm","材质":"塑料","规格/类型":"Schedule 40","管内底标高":"44","剖面":"1","面积":"0 m²","相对粗糙度":"0.014746","图像":"<无>","总体大小":"50 mmø","隔热层厚度":"0 mm","卫浴装置当量":"0","外径":"60 mm","内径":"53 mm","尺寸":"50 mmø","标记":"36","创建的阶段":"阶段 1","拆除的阶段":"无","水平对正":"中心","垂直对正":"中","参照标高":"发泡顶","偏移":"-170","开始偏移":"-170","端点偏移":"-170","长度":"194","坡度":"0.00%","类型图像":"<无>","成本":"0.00"}},{"uuid":"b12e49b8-326c-4c85-982a-112e4bf5174b-0003a851","name":"","familyName":"管道类型","typeName":"","typeId":-1,"revitId":"239697","type":"Element","category":"OST_PipeCurvesCenterLine","properties":{"Category":"中心线","Name":"","ElementPoint":null,"ElementRotation":null,"Mirrored":null,"HandFlipped":null,"HandOrientation":null,"FacingFlipped":null,"FacingOrientation":null,"Translation":null,"matrix":null,"BoundingBox":"(-3.399687243, -0.243917998, 0.229658793),(-3.399687243, -0.879601329, 0.229658793)","系统分类":"卫生设备","系统类型":"卫生设备","系统名称":"卫生设备 1","管段":"塑料 - Schedule 40","直径":"50 mm","连接类型":"常规","粗糙度":"0.774 mm","材质":"塑料","规格/类型":"Schedule 40","管内底标高":"44","剖面":"0","面积":"0 m²","相对粗糙度":"0","图像":"<无>","总体大小":"50 mmø","隔热层厚度":"0 mm","卫浴装置当量":"0","外径":"60 mm","内径":"53 mm","尺寸":"50 mmø","标记":"36","创建的阶段":"阶段 1","拆除的阶段":"无","水平对正":"中心","垂直对正":"中","参照标高":"发泡顶","偏移":"-170","开始偏移":"-170","端点偏移":"-170","长度":"194","坡度":"0.00%"}},{"uuid":"7c12137a-d7a0-4210-b7da-25589395af0a-0003bd54","name":"标准","familyName":"弯头 - PVC - Sch 40","typeName":"标准","typeId":160631,"revitId":"245076","type":"FamilyInstance","category":"OST_PipeFitting","properties":{"Category":"管件","Name":"标准","ElementPoint":"(-3.399687243, -0.032980498, 0.229658793)","ElementRotation":"(0.000000000, 0.000000000, -1.000000000)","Mirrored":"False","HandFlipped":"False","HandOrientation":"(0.000000000, 0.000000000, -1.000000000)","FacingFlipped":"False","FacingOrientation":"(0.000000000, -1.000000000, 0.000000000)","Translation":"(-3.399687243, -0.032980498, 0.229658793)","matrix":"0,0,-1,0,0,-1,0,0,-1,0,0,0,-1.03622467160649,-0.0100524558567386,0.0700000000000026,1","BoundingBox":"(-3.287687243, 0.079019502, 0.440596293),(-3.511687243, -0.243917998, 0.117658793)","总体大小":"50 mmø-50 mmø","隔热层厚度":"0 mm","压降":"0.0 Pa","标高":"展示层面","主体":"标高 : 展示层面","偏移":"70","创建的阶段":"阶段 1","拆除的阶段":"无","系统分类":"卫生设备","系统类型":"卫生设备","系统名称":"卫生设备 1","损失方法":"3bf616f9-6b98-4a21-80ff-da1120c8f6d6","使用注释比例":"否","记号尺寸":"27 mm","套管外径":"68 mm","公称半径":"25 mm","公称直径":"50 mm","中心到端点":"61 mm","套管长度":"29 mm","角度":"90.00°","尺寸":"50 mmø-50 mmø","图像":"<无>","标记":"16","套管外半径":"34 mm","找不到套管外径":"69 mm","找不到套管长度":"35 mm","长度 1":"64 mm","找不到中心到端点":"68 mm","中心到端点标签":"64 mm","中心半径":"35 mm","角度 1":"90.00°","IsCustom":"否","K 系数":"0","类型图像":"<无>","成本":"0.00","查找表名称":"M_Elbow - PVC - Sch 40"}},{"uuid":"7c12137a-d7a0-4210-b7da-25589395af0a-0003bd55","name":"","familyName":"弯头 - PVC - Sch 40","typeName":"","typeId":-1,"revitId":"245077","type":"Element","category":"OST_PipeFittingCenterLine","properties":{"Category":"中心线","Name":"","ElementPoint":null,"ElementRotation":null,"Mirrored":null,"HandFlipped":null,"HandOrientation":null,"FacingFlipped":null,"FacingOrientation":null,"Translation":null,"matrix":null,"BoundingBox":"(-3.399687243, -0.032980498, 0.440596293),(-3.399687243, -0.243917998, 0.229658793)","记号尺寸":"27 mm","套管外半径":"34 mm","找不到套管外径":"69 mm","套管外径":"68 mm","找不到套管长度":"35 mm","长度 1":"64 mm","公称半径":"25 mm","公称直径":"50 mm","找不到中心到端点":"68 mm","中心到端点标签":"64 mm","中心到端点":"61 mm","中心半径":"35 mm","套管长度":"29 mm","角度 1":"90.00°","角度":"90.00°","标高":"展示层面","主体":"标高 : 展示层面","偏移":"70","系统分类":"卫生设备","系统类型":"卫生设备","系统名称":"卫生设备 1","损失方法":"3bf616f9-6b98-4a21-80ff-da1120c8f6d6","图像":"<无>","总体大小":"50 mmø-50 mmø","隔热层厚度":"0 mm","压降":"0.0 Pa","使用注释比例":"否","尺寸":"50 mmø-50 mmø","IsCustom":"否","标记":"16","创建的阶段":"阶段 1","拆除的阶段":"无"}},{"uuid":"7c12137a-d7a0-4210-b7da-25589395af0a-0003be1c","name":"PVC","familyName":"管道类型","typeName":"PVC","typeId":237677,"revitId":"245276","type":"Pipe","category":"OST_PipeCurves","properties":{"Category":"管道","Name":"PVC","ElementPoint":null,"ElementRotation":null,"Mirrored":null,"HandFlipped":null,"HandOrientation":null,"FacingFlipped":null,"FacingOrientation":null,"Translation":null,"matrix":null,"BoundingBox":"(-0.791490282, -3.140501348, 1.771653543),(-0.989406948, -3.338418015, 0.963972441)","系统分类":"其他","系统类型":"排水系统","系统名称":"排水系统 3","管段":"塑料 - Schedule 40","直径":"50 mm","连接类型":"常规","粗糙度":"0.774 mm","材质":"塑料","规格/类型":"Schedule 40","管内底标高":"294","剖面":"10","面积":"0 m²","相对粗糙度":"0.014746","图像":"<无>","总体大小":"50 mmø","隔热层厚度":"0 mm","外径":"60 mm","内径":"53 mm","尺寸":"50 mmø","标记":"41","创建的阶段":"阶段 1","拆除的阶段":"无","水平对正":"中心","垂直对正":"中","参照标高":"发泡顶","偏移":"54","开始偏移":"54","端点偏移":"300","长度":"246","坡度":"0.00%","类型图像":"<无>","成本":"0.00"}},{"uuid":"7c12137a-d7a0-4210-b7da-25589395af0a-0003be1d","name":"","familyName":"管道类型","typeName":"","typeId":-1,"revitId":"245277","type":"Element","category":"OST_PipeCurvesCenterLine","properties":{"Category":"中心线","Name":"","ElementPoint":null,"ElementRotation":null,"Mirrored":null,"HandFlipped":null,"HandOrientation":null,"FacingFlipped":null,"FacingOrientation":null,"Translation":null,"matrix":null,"BoundingBox":"(-0.890448615, -3.239459682, 1.771653543),(-0.890448615, -3.239459682, 0.963972441)","系统分类":"其他","系统类型":"排水系统","系统名称":"排水系统 3","管段":"塑料 - Schedule 40","直径":"50 mm","连接类型":"常规","粗糙度":"0.774 mm","材质":"塑料","规格/类型":"Schedule 40","管内底标高":"294","剖面":"0","面积":"0 m²","相对粗糙度":"0","图像":"<无>","总体大小":"50 mmø","隔热层厚度":"0 mm","外径":"60 mm","内径":"53 mm","尺寸":"50 mmø","标记":"41","创建的阶段":"阶段 1","拆除的阶段":"无","水平对正":"中心","垂直对正":"中","参照标高":"发泡顶","偏移":"54","开始偏移":"54","端点偏移":"300","长度":"246","坡度":"0.00%"}},{"uuid":"7c12137a-d7a0-4210-b7da-25589395af0a-0003be1e","name":"PVC防水","familyName":"管道类型","typeName":"PVC防水","typeId":246139,"revitId":"245278","type":"Pipe","category":"OST_PipeCurves","properties":{"Category":"管道","Name":"PVC防水","ElementPoint":null,"ElementRotation":null,"Mirrored":null,"HandFlipped":null,"HandOrientation":null,"FacingFlipped":null,"FacingOrientation":null,"Translation":null,"matrix":null,"BoundingBox":"(-0.770656948, -3.119668015, 1.443569554),(-1.010240282, -3.359251348, 0.426509186)","系统分类":"其他","系统类型":"排水系统","系统名称":"排水系统 4","管段":"塑料 - Schedule 40","直径":"65 mm","连接类型":"常规","粗糙度":"0.774 mm","材质":"塑料","规格/类型":"Schedule 40","管内底标高":"130","剖面":"1","面积":"0 m²","相对粗糙度":"0.012345","图像":"<无>","总体大小":"65 mmø","隔热层厚度":"0 mm","外径":"73 mm","内径":"63 mm","尺寸":"65 mmø","标记":"42","创建的阶段":"阶段 1","拆除的阶段":"无","水平对正":"中心","垂直对正":"中","参照标高":"发泡顶","偏移":"-110","开始偏移":"-110","端点偏移":"200","长度":"310","坡度":"0.00%","类型图像":"<无>","成本":"0.00"}},{"uuid":"7c12137a-d7a0-4210-b7da-25589395af0a-0003be1f","name":"","familyName":"管道类型","typeName":"","typeId":-1,"revitId":"245279","type":"Element","category":"OST_PipeCurvesCenterLine","properties":{"Category":"中心线","Name":"","ElementPoint":null,"ElementRotation":null,"Mirrored":null,"HandFlipped":null,"HandOrientation":null,"FacingFlipped":null,"FacingOrientation":null,"Translation":null,"matrix":null,"BoundingBox":"(-0.890448615, -3.239459682, 1.443569554),(-0.890448615, -3.239459682, 0.426509186)","系统分类":"其他","系统类型":"排水系统","系统名称":"排水系统 4","管段":"塑料 - Schedule 40","直径":"65 mm","连接类型":"常规","粗糙度":"0.774 mm","材质":"塑料","规格/类型":"Schedule 40","管内底标高":"130","剖面":"0","面积":"0 m²","相对粗糙度":"0","图像":"<无>","总体大小":"65 mmø","隔热层厚度":"0 mm","外径":"73 mm","内径":"63 mm","尺寸":"65 mmø","标记":"42","创建的阶段":"阶段 1","拆除的阶段":"无","水平对正":"中心","垂直对正":"中","参照标高":"发泡顶","偏移":"-110","开始偏移":"-110","端点偏移":"200","长度":"310","坡度":"0.00%"}},{"uuid":"7c12137a-d7a0-4210-b7da-25589395af0a-0003be24","name":"排水系统 3","familyName":"管道系统","typeName":"排水系统 3","typeId":238384,"revitId":"245284","type":"PipingSystem","category":"OST_PipingSystem","properties":{"Category":"管道系统","Name":"排水系统 3","ElementPoint":null,"ElementRotation":null,"Mirrored":null,"HandFlipped":null,"HandOrientation":null,"FacingFlipped":null,"FacingOrientation":null,"Translation":null,"matrix":null,"BoundingBox":"(0.479482231, 0.320398671, 5.399475066),(-4.769618089, -4.609390528, -1.288091207)","图像":"<无>","图元数":"0","系统名称":"排水系统 3","体积":"17.7 L","类型图像":"<无>","双线下降符号":"阴阳","双线上升符号":"轮廓","单线下降符号":"弯曲 - ¾ 圆","单线上升符号":"轮廓","单线 T 形三通向上符号":"轮廓","单线 T 形三通向下符号":"T 形三通 - 半圆","计算":"无","系统分类":"其他","材质":"<按类别>"}},{"uuid":"7c12137a-d7a0-4210-b7da-25589395af0a-0003be25","name":"排水系统 4","familyName":"管道系统","typeName":"排水系统 4","typeId":238384,"revitId":"245285","type":"PipingSystem","category":"OST_PipingSystem","properties":{"Category":"管道系统","Name":"排水系统 4","ElementPoint":null,"ElementRotation":null,"Mirrored":null,"HandFlipped":null,"HandOrientation":null,"FacingFlipped":null,"FacingOrientation":null,"Translation":null,"matrix":null,"BoundingBox":"(0.429343052, -1.919668015, 2.643569554),(-2.210240282, -4.559251348, -0.773490814)","图像":"<无>","图元数":"0","系统名称":"排水系统 4","体积":"1.0 L","类型图像":"<无>","双线下降符号":"阴阳","双线上升符号":"轮廓","单线下降符号":"弯曲 - ¾ 圆","单线上升符号":"轮廓","单线 T 形三通向上符号":"轮廓","单线 T 形三通向下符号":"T 形三通 - 半圆","计算":"无","系统分类":"其他","材质":"<按类别>"}},{"uuid":"7c12137a-d7a0-4210-b7da-25589395af0a-0003bff6","name":"标准","familyName":"三通 - PVC - Sch 40","typeName":"标准","typeId":243974,"revitId":"245750","type":"FamilyInstance","category":"OST_PipeFitting","properties":{"Category":"管件","Name":"标准","ElementPoint":"(-3.399687243, -1.597019144, 0.229658793)","ElementRotation":"(0.000000000, -1.000000000, 0.000000000)","Mirrored":"False","HandFlipped":"False","HandOrientation":"(0.000000000, -1.000000000, 0.000000000)","FacingFlipped":"False","FacingOrientation":"(-1.000000000, 0.000000000, 0.000000000)","Translation":"(-3.399687243, -1.597019144, 0.229658793)","matrix":"0,-1,0,0,-1,0,0,0,0,0,-1,0,-1.03622467160653,-0.486771435050133,0.0699999999999908,1","BoundingBox":"(-3.081937243, -1.279269144, 0.395033793),(-3.565062243, -1.914769144, 0.064283793)","总体大小":"80 mmø-80 mmø-80 mmø","隔热层厚度":"0 mm","压降":"0.0 Pa","标高":"发泡顶","主体":"标高 : 发泡顶","偏移":"-170","创建的阶段":"阶段 1","拆除的阶段":"无","系统分类":"其他","系统类型":"排水系统","系统名称":"排水系统 3","损失方法":"3bf616f9-6b98-4a21-80ff-da1120c8f6d6","使用注释比例":"否","记号尺寸":"40 mm","套管外径":"101 mm","公称半径":"40 mm","公称直径":"80 mm","中心到端点":"97 mm","角度":"90.00°","尺寸":"80 mmø-80 mmø-80 mmø","图像":"<无>","标记":"17","套管外半径":"50 mm","中心到端点标签":"97 mm","角度 1":"90.00°","IsCustom":"否","K 系数":"0","类型图像":"<无>","成本":"0.00","查找表名称":"M_Tee - PVC - Sch 40"}},{"uuid":"7c12137a-d7a0-4210-b7da-25589395af0a-0003bff7","name":"","familyName":"三通 - PVC - Sch 40","typeName":"","typeId":-1,"revitId":"245751","type":"Element","category":"OST_PipeFittingCenterLine","properties":{"Category":"中心线","Name":"","ElementPoint":null,"ElementRotation":null,"Mirrored":null,"HandFlipped":null,"HandOrientation":null,"FacingFlipped":null,"FacingOrientation":null,"Translation":null,"matrix":null,"BoundingBox":"(-3.081937243, -1.279269144, 0.229658793),(-3.399687243, -1.914769144, 0.229658793)","记号尺寸":"40 mm","套管外半径":"50 mm","套管外径":"101 mm","公称半径":"40 mm","公称直径":"80 mm","中心到端点标签":"97 mm","中心到端点":"97 mm","角度":"90.00°","角度 1":"90.00°","标高":"发泡顶","主体":"标高 : 发泡顶","偏移":"-170","系统分类":"其他","系统类型":"排水系统","系统名称":"排水系统 3","损失方法":"3bf616f9-6b98-4a21-80ff-da1120c8f6d6","图像":"<无>","总体大小":"80 mmø-80 mmø-80 mmø","隔热层厚度":"0 mm","压降":"0.0 Pa","使用注释比例":"否","尺寸":"80 mmø-80 mmø-80 mmø","IsCustom":"否","标记":"17","创建的阶段":"阶段 1","拆除的阶段":"无"}},{"uuid":"7c12137a-d7a0-4210-b7da-25589395af0a-0003bff9","name":"标准","familyName":"变径管接头 - PVC - Sch 40","typeName":"标准","typeId":241616,"revitId":"245753","type":"FamilyInstance","category":"OST_PipeFitting","properties":{"Category":"管件","Name":"标准","ElementPoint":"(-3.399687243, -1.279269144, 0.229658793)","ElementRotation":"(0.000000000, 1.000000000, 0.000000000)","Mirrored":"False","HandFlipped":"False","HandOrientation":"(0.000000000, 1.000000000, 0.000000000)","FacingFlipped":"False","FacingOrientation":"(-1.000000000, 0.000000000, 0.000000000)","Translation":"(-3.399687243, -1.279269144, 0.229658793)","matrix":"0,1,0,0,-1,0,0,0,0,0,1,0,-1.03622467160651,-0.389921235050159,0.0699999999999928,1","BoundingBox":"(-3.229756397, -0.879601329, 0.399589639),(-3.569618089, -1.279269144, 0.059727947)","总体大小":"80 mmø-50 mmø","隔热层厚度":"0 mm","压降":"0.0 Pa","标高":"发泡顶","主体":"标高 : 发泡顶","偏移":"-170","创建的阶段":"阶段 1","拆除的阶段":"无","系统分类":"其他","系统类型":"排水系统","系统名称":"排水系统 3","损失方法":"3bf616f9-6b98-4a21-80ff-da1120c8f6d6","使用注释比例":"否","长度":"93 mm","记号尺寸 2":"28 mm","记号尺寸 1":"41 mm","偏移宽度":"40.0000 mm","偏移高度":"40.0000 mm","公称半径 2":"25 mm","公称直径 2":"50 mm","套管长度 2":"48 mm","套管外径 2":"70 mm","套管外径 1":"104 mm","公称半径 1":"40 mm","公称直径 1":"80 mm","套管长度 1":"71 mm","尺寸":"80 mmø-50 mmø","图像":"<无>","标记":"18","可见性 3":"是","可见性 2":"否","可见性 1":"否","最大公称直径 12":"80 mm","套管外半径 2":"35 mm","套管外半径 1":"52 mm","长度 1":"3048 mm","长度标签":"122 mm","长度 2":"3048 mm","IsCustom":"否","K 系数":"0","类型图像":"<无>","成本":"0.00","查找表名称":"M_Coupling Reducing - PVC - Sch 40"}},{"uuid":"7c12137a-d7a0-4210-b7da-25589395af0a-0003bffa","name":"","familyName":"变径管接头 - PVC - Sch 40","typeName":"","typeId":-1,"revitId":"245754","type":"Element","category":"OST_PipeFittingCenterLine","properties":{"Category":"中心线","Name":"","ElementPoint":null,"ElementRotation":null,"Mirrored":null,"HandFlipped":null,"HandOrientation":null,"FacingFlipped":null,"FacingOrientation":null,"Translation":null,"matrix":null,"BoundingBox":"(-3.399687243, -0.879601329, 0.229658793),(-3.399687243, -1.279269144, 0.229658793)","可见性 3":"是","可见性 2":"否","可见性 1":"否","长度":"93 mm","记号尺寸 2":"28 mm","记号尺寸 1":"41 mm","公称半径 2":"25 mm","公称直径 2":"50 mm","最大公称直径 12":"80 mm","套管长度 2":"48 mm","套管外半径 2":"35 mm","套管外半径 1":"52 mm","套管外径 2":"70 mm","套管外径 1":"104 mm","长度 1":"3048 mm","长度标签":"122 mm","公称半径 1":"40 mm","公称直径 1":"80 mm","长度 2":"3048 mm","套管长度 1":"71 mm","标高":"发泡顶","主体":"标高 : 发泡顶","偏移":"-170","系统分类":"其他","系统类型":"排水系统","系统名称":"排水系统 3","损失方法":"3bf616f9-6b98-4a21-80ff-da1120c8f6d6","图像":"<无>","总体大小":"80 mmø-50 mmø","隔热层厚度":"0 mm","压降":"0.0 Pa","使用注释比例":"否","尺寸":"80 mmø-50 mmø","IsCustom":"否","偏移高度":"40.0000 mm","偏移宽度":"40.0000 mm","标记":"18","创建的阶段":"阶段 1","拆除的阶段":"无"}},{"uuid":"7c12137a-d7a0-4210-b7da-25589395af0a-0003c007","name":"PVC","familyName":"管道类型","typeName":"PVC","typeId":237677,"revitId":"245767","type":"Pipe","category":"OST_PipeCurves","properties":{"Category":"管道","Name":"PVC","ElementPoint":null,"ElementRotation":null,"Mirrored":null,"HandFlipped":null,"HandOrientation":null,"FacingFlipped":null,"FacingOrientation":null,"Translation":null,"matrix":null,"BoundingBox":"(-3.253853909, -1.914769144, 0.375492126),(-3.545520576, -2.904813848, 0.083825459)","系统分类":"其他","系统类型":"排水系统","系统名称":"排水系统 3","管段":"塑料 - Schedule 40","直径":"80 mm","连接类型":"常规","粗糙度":"0.774 mm","材质":"塑料","规格/类型":"Schedule 40","管内底标高":"31","剖面":"1","面积":"0 m²","相对粗糙度":"0.009935","图像":"<无>","总体大小":"80 mmø","隔热层厚度":"0 mm","外径":"89 mm","内径":"78 mm","尺寸":"80 mmø","标记":"45","创建的阶段":"阶段 1","拆除的阶段":"无","水平对正":"中心","垂直对正":"中","参照标高":"展示层面","偏移":"70","开始偏移":"70","端点偏移":"70","长度":"302","坡度":"0.00%","类型图像":"<无>","成本":"0.00"}},{"uuid":"7c12137a-d7a0-4210-b7da-25589395af0a-0003c008","name":"","familyName":"管道类型","typeName":"","typeId":-1,"revitId":"245768","type":"Element","category":"OST_PipeCurvesCenterLine","properties":{"Category":"中心线","Name":"","ElementPoint":null,"ElementRotation":null,"Mirrored":null,"HandFlipped":null,"HandOrientation":null,"FacingFlipped":null,"FacingOrientation":null,"Translation":null,"matrix":null,"BoundingBox":"(-3.399687243, -1.914769144, 0.229658793),(-3.399687243, -2.904813848, 0.229658793)","系统分类":"其他","系统类型":"排水系统","系统名称":"排水系统 3","管段":"塑料 - Schedule 40","直径":"80 mm","连接类型":"常规","粗糙度":"0.774 mm","材质":"塑料","规格/类型":"Schedule 40","管内底标高":"31","剖面":"0","面积":"0 m²","相对粗糙度":"0","图像":"<无>","总体大小":"80 mmø","隔热层厚度":"0 mm","外径":"89 mm","内径":"78 mm","尺寸":"80 mmø","标记":"45","创建的阶段":"阶段 1","拆除的阶段":"无","水平对正":"中心","垂直对正":"中","参照标高":"展示层面","偏移":"70","开始偏移":"70","端点偏移":"70","长度":"302","坡度":"0.00%"}},{"uuid":"7c12137a-d7a0-4210-b7da-25589395af0a-0003c011","name":"PVC","familyName":"管道类型","typeName":"PVC","typeId":237677,"revitId":"245777","type":"Pipe","category":"OST_PipeCurves","properties":{"Category":"管道","Name":"PVC","ElementPoint":null,"ElementRotation":null,"Mirrored":null,"HandFlipped":null,"HandOrientation":null,"FacingFlipped":null,"FacingOrientation":null,"Translation":null,"matrix":null,"BoundingBox":"(-1.225094448, -3.093626348, 0.375492126),(-3.065041409, -3.385293015, 0.083825459)","系统分类":"其他","系统类型":"排水系统","系统名称":"排水系统 3","管段":"塑料 - Schedule 40","直径":"80 mm","连接类型":"常规","粗糙度":"0.774 mm","材质":"塑料","规格/类型":"Schedule 40","管内底标高":"31","剖面":"1","面积":"0 m²","相对粗糙度":"0.009935","图像":"<无>","总体大小":"80 mmø","隔热层厚度":"0 mm","外径":"89 mm","内径":"78 mm","尺寸":"80 mmø","标记":"46","创建的阶段":"阶段 1","拆除的阶段":"无","水平对正":"中心","垂直对正":"中","参照标高":"展示层面","偏移":"70","开始偏移":"70","端点偏移":"70","长度":"561","坡度":"0.00%","类型图像":"<无>","成本":"0.00"}},{"uuid":"7c12137a-d7a0-4210-b7da-25589395af0a-0003c012","name":"","familyName":"管道类型","typeName":"","typeId":-1,"revitId":"245778","type":"Element","category":"OST_PipeCurvesCenterLine","properties":{"Category":"中心线","Name":"","ElementPoint":null,"ElementRotation":null,"Mirrored":null,"HandFlipped":null,"HandOrientation":null,"FacingFlipped":null,"FacingOrientation":null,"Translation":null,"matrix":null,"BoundingBox":"(-1.225094448, -3.239459682, 0.229658793),(-3.065041409, -3.239459682, 0.229658793)","系统分类":"其他","系统类型":"排水系统","系统名称":"排水系统 3","管段":"塑料 - Schedule 40","直径":"80 mm","连接类型":"常规","粗糙度":"0.774 mm","材质":"塑料","规格/类型":"Schedule 40","管内底标高":"31","剖面":"0","面积":"0 m²","相对粗糙度":"0","图像":"<无>","总体大小":"80 mmø","隔热层厚度":"0 mm","外径":"89 mm","内径":"78 mm","尺寸":"80 mmø","标记":"46","创建的阶段":"阶段 1","拆除的阶段":"无","水平对正":"中心","垂直对正":"中","参照标高":"展示层面","偏移":"70","开始偏移":"70","端点偏移":"70","长度":"561","坡度":"0.00%"}},{"uuid":"7c12137a-d7a0-4210-b7da-25589395af0a-0003c01b","name":"标准","familyName":"弯头 - PVC - Sch 40","typeName":"标准","typeId":160631,"revitId":"245787","type":"FamilyInstance","category":"OST_PipeFitting","properties":{"Category":"管件","Name":"标准","ElementPoint":"(-3.399687243, -3.239459682, 0.229658793)","ElementRotation":"(0.000000000, -1.000000000, 0.000000000)","Mirrored":"False","HandFlipped":"False","HandOrientation":"(0.000000000, -1.000000000, 0.000000000)","FacingFlipped":"False","FacingOrientation":"(1.000000000, 0.000000000, 0.000000000)","Translation":"(-3.399687243, -3.239459682, 0.229658793)","matrix":"0,-1,0,0,1,0,0,0,0,0,1,0,-1.0362246716065,-0.987387310986982,0.0699999999999826,1","BoundingBox":"(-3.065041409, -2.904813848, 0.395033793),(-3.565062243, -3.404834682, 0.064283793)","总体大小":"80 mmø-80 mmø","隔热层厚度":"0 mm","压降":"0.0 Pa","标高":"展示层面","主体":"标高 : 展示层面","偏移":"70","创建的阶段":"阶段 1","拆除的阶段":"无","系统分类":"其他","系统类型":"排水系统","系统名称":"排水系统 3","损失方法":"3bf616f9-6b98-4a21-80ff-da1120c8f6d6","使用注释比例":"否","记号尺寸":"40 mm","套管外径":"101 mm","公称半径":"40 mm","公称直径":"80 mm","中心到端点":"97 mm","套管长度":"51 mm","角度":"90.00°","尺寸":"80 mmø-80 mmø","图像":"<无>","标记":"21","套管外半径":"50 mm","找不到套管外径":"102 mm","找不到套管长度":"49 mm","长度 1":"102 mm","找不到中心到端点":"98 mm","中心到端点标签":"102 mm","中心半径":"51 mm","角度 1":"90.00°","IsCustom":"否","K 系数":"0","类型图像":"<无>","成本":"0.00","查找表名称":"M_Elbow - PVC - Sch 40"}},{"uuid":"7c12137a-d7a0-4210-b7da-25589395af0a-0003c01c","name":"","familyName":"弯头 - PVC - Sch 40","typeName":"","typeId":-1,"revitId":"245788","type":"Element","category":"OST_PipeFittingCenterLine","properties":{"Category":"中心线","Name":"","ElementPoint":null,"ElementRotation":null,"Mirrored":null,"HandFlipped":null,"HandOrientation":null,"FacingFlipped":null,"FacingOrientation":null,"Translation":null,"matrix":null,"BoundingBox":"(-3.065041409, -2.904813848, 0.229658793),(-3.399687243, -3.239459682, 0.229658793)","记号尺寸":"40 mm","套管外半径":"50 mm","找不到套管外径":"102 mm","套管外径":"101 mm","找不到套管长度":"49 mm","长度 1":"102 mm","公称半径":"40 mm","公称直径":"80 mm","找不到中心到端点":"98 mm","中心到端点标签":"102 mm","中心到端点":"97 mm","中心半径":"51 mm","套管长度":"51 mm","角度 1":"90.00°","角度":"90.00°","标高":"展示层面","主体":"标高 : 展示层面","偏移":"70","系统分类":"其他","系统类型":"排水系统","系统名称":"排水系统 3","损失方法":"3bf616f9-6b98-4a21-80ff-da1120c8f6d6","图像":"<无>","总体大小":"80 mmø-80 mmø","隔热层厚度":"0 mm","压降":"0.0 Pa","使用注释比例":"否","尺寸":"80 mmø-80 mmø","IsCustom":"否","标记":"21","创建的阶段":"阶段 1","拆除的阶段":"无"}},{"uuid":"7c12137a-d7a0-4210-b7da-25589395af0a-0003c15f","name":"标准","familyName":"弯头 - PVC - Sch 40","typeName":"标准","typeId":160631,"revitId":"246111","type":"FamilyInstance","category":"OST_PipeFitting","properties":{"Category":"管件","Name":"标准","ElementPoint":"(-0.890448615, -3.239459682, 0.229658793)","ElementRotation":"(1.000000000, 0.000000000, 0.000000000)","Mirrored":"False","HandFlipped":"False","HandOrientation":"(1.000000000, 0.000000000, 0.000000000)","FacingFlipped":"False","FacingOrientation":"(0.000000000, 0.000000000, 1.000000000)","Translation":"(-0.890448615, -3.239459682, 0.229658793)","matrix":"1,0,0,0,0,0,1,0,0,-1,0,0,-0.271408737859302,-0.987387310986997,0.0699999999999978,1","BoundingBox":"(-0.725073615, -3.074084682, 0.564304626),(-1.225094448, -3.404834682, 0.064283793)","总体大小":"80 mmø-80 mmø","隔热层厚度":"0 mm","压降":"0.0 Pa","标高":"展示层面","主体":"标高 : 展示层面","偏移":"70","创建的阶段":"阶段 1","拆除的阶段":"无","系统分类":"其他","系统类型":"排水系统","系统名称":"排水系统 3","损失方法":"3bf616f9-6b98-4a21-80ff-da1120c8f6d6","使用注释比例":"否","记号尺寸":"40 mm","套管外径":"101 mm","公称半径":"40 mm","公称直径":"80 mm","中心到端点":"97 mm","套管长度":"51 mm","角度":"90.00°","尺寸":"80 mmø-80 mmø","图像":"<无>","标记":"22","套管外半径":"50 mm","找不到套管外径":"102 mm","找不到套管长度":"49 mm","长度 1":"102 mm","找不到中心到端点":"98 mm","中心到端点标签":"102 mm","中心半径":"51 mm","角度 1":"90.00°","IsCustom":"否","K 系数":"0","类型图像":"<无>","成本":"0.00","查找表名称":"M_Elbow - PVC - Sch 40"}},{"uuid":"7c12137a-d7a0-4210-b7da-25589395af0a-0003c160","name":"","familyName":"弯头 - PVC - Sch 40","typeName":"","typeId":-1,"revitId":"246112","type":"Element","category":"OST_PipeFittingCenterLine","properties":{"Category":"中心线","Name":"","ElementPoint":null,"ElementRotation":null,"Mirrored":null,"HandFlipped":null,"HandOrientation":null,"FacingFlipped":null,"FacingOrientation":null,"Translation":null,"matrix":null,"BoundingBox":"(-0.890448615, -3.239459682, 0.564304626),(-1.225094448, -3.239459682, 0.229658793)","记号尺寸":"40 mm","套管外半径":"50 mm","找不到套管外径":"102 mm","套管外径":"101 mm","找不到套管长度":"49 mm","长度 1":"102 mm","公称半径":"40 mm","公称直径":"80 mm","找不到中心到端点":"98 mm","中心到端点标签":"102 mm","中心到端点":"97 mm","中心半径":"51 mm","套管长度":"51 mm","角度 1":"90.00°","角度":"90.00°","标高":"展示层面","主体":"标高 : 展示层面","偏移":"70","系统分类":"其他","系统类型":"排水系统","系统名称":"排水系统 3","损失方法":"3bf616f9-6b98-4a21-80ff-da1120c8f6d6","图像":"<无>","总体大小":"80 mmø-80 mmø","隔热层厚度":"0 mm","压降":"0.0 Pa","使用注释比例":"否","尺寸":"80 mmø-80 mmø","IsCustom":"否","标记":"22","创建的阶段":"阶段 1","拆除的阶段":"无"}},{"uuid":"7c12137a-d7a0-4210-b7da-25589395af0a-0003c248","name":"PVC防水","familyName":"管道类型","typeName":"PVC防水","typeId":246139,"revitId":"246344","type":"Pipe","category":"OST_PipeCurves","properties":{"Category":"管道","Name":"PVC防水","ElementPoint":null,"ElementRotation":null,"Mirrored":null,"HandFlipped":null,"HandOrientation":null,"FacingFlipped":null,"FacingOrientation":null,"Translation":null,"matrix":null,"BoundingBox":"(-3.207027639, 0.155203093, 1.049868766),(-3.582027639, -0.219796907, 0.426509186)","系统分类":"其他","系统类型":"排水系统","系统名称":"排水系统 1","管段":"塑料 - Schedule 40","直径":"100 mm","连接类型":"常规","粗糙度":"0.774 mm","材质":"塑料","规格/类型":"Schedule 40","管内底标高":"130","剖面":"1","面积":"0 m²","相对粗糙度":"0.007571","图像":"<无>","总体大小":"100 mmø","隔热层厚度":"0 mm","外径":"114 mm","内径":"102 mm","尺寸":"100 mmø","标记":"47","创建的阶段":"阶段 1","拆除的阶段":"无","水平对正":"中心","垂直对正":"中","参照标高":"发泡顶","偏移":"-110","开始偏移":"-110","端点偏移":"80","长度":"190","坡度":"0.00%","类型图像":"<无>","成本":"0.00"}},{"uuid":"7c12137a-d7a0-4210-b7da-25589395af0a-0003c249","name":"","familyName":"管道类型","typeName":"","typeId":-1,"revitId":"246345","type":"Element","category":"OST_PipeCurvesCenterLine","properties":{"Category":"中心线","Name":"","ElementPoint":null,"ElementRotation":null,"Mirrored":null,"HandFlipped":null,"HandOrientation":null,"FacingFlipped":null,"FacingOrientation":null,"Translation":null,"matrix":null,"BoundingBox":"(-3.394527639, -0.032296907, 1.049868766),(-3.394527639, -0.032296907, 0.426509186)","系统分类":"其他","系统类型":"排水系统","系统名称":"排水系统 1","管段":"塑料 - Schedule 40","直径":"100 mm","连接类型":"常规","粗糙度":"0.774 mm","材质":"塑料","规格/类型":"Schedule 40","管内底标高":"130","剖面":"0","面积":"0 m²","相对粗糙度":"0","图像":"<无>","总体大小":"100 mmø","隔热层厚度":"0 mm","外径":"114 mm","内径":"102 mm","尺寸":"100 mmø","标记":"47","创建的阶段":"阶段 1","拆除的阶段":"无","水平对正":"中心","垂直对正":"中","参照标高":"发泡顶","偏移":"-110","开始偏移":"-110","端点偏移":"80","长度":"190","坡度":"0.00%"}},{"uuid":"7c12137a-d7a0-4210-b7da-25589395af0a-0003c24a","name":"排水系统 1","familyName":"管道系统","typeName":"排水系统 1","typeId":238384,"revitId":"246346","type":"PipingSystem","category":"OST_PipingSystem","properties":{"Category":"管道系统","Name":"排水系统 1","ElementPoint":null,"ElementRotation":null,"Mirrored":null,"HandFlipped":null,"HandOrientation":null,"FacingFlipped":null,"FacingOrientation":null,"Translation":null,"matrix":null,"BoundingBox":"(-2.007027639, 1.355203093, 2.249868766),(-4.782027639, -1.419796907, -0.773490814)","图像":"<无>","图元数":"0","系统名称":"排水系统 1","体积":"1.6 L","类型图像":"<无>","双线下降符号":"阴阳","双线上升符号":"轮廓","单线下降符号":"弯曲 - ¾ 圆","单线上升符号":"轮廓","单线 T 形三通向上符号":"轮廓","单线 T 形三通向下符号":"T 形三通 - 半圆","计算":"无","系统分类":"其他","材质":"<按类别>"}},{"uuid":"7c12137a-d7a0-4210-b7da-25589395af0a-0003c29f","name":"标准","familyName":"三通 - PVC - Sch 40","typeName":"标准","typeId":243974,"revitId":"246431","type":"FamilyInstance","category":"OST_PipeFitting","properties":{"Category":"管件","Name":"标准","ElementPoint":"(-0.890448615, -1.597019144, 0.229658793)","ElementRotation":"(0.000000000, 0.000000000, -1.000000000)","Mirrored":"False","HandFlipped":"False","HandOrientation":"(0.000000000, 0.000000000, -1.000000000)","FacingFlipped":"False","FacingOrientation":"(1.000000000, 0.000000000, 0.000000000)","Translation":"(-0.890448615, -1.597019144, 0.229658793)","matrix":"0,0,-1,0,1,0,0,0,0,-1,0,0,-0.271408737859271,-0.486771435050139,0.0699999999999987,1","BoundingBox":"(-0.725073615, -1.431644144, 0.547408793),(-1.208198615, -1.762394144, -0.088091207)","总体大小":"80 mmø-80 mmø-80 mmø","隔热层厚度":"0 mm","压降":"0.0 Pa","标高":"发泡顶","主体":"标高 : 发泡顶","偏移":"-170","创建的阶段":"阶段 1","拆除的阶段":"无","系统分类":"其他","系统类型":"排水系统","系统名称":"排水系统 3","损失方法":"3bf616f9-6b98-4a21-80ff-da1120c8f6d6","使用注释比例":"否","记号尺寸":"40 mm","套管外径":"101 mm","公称半径":"40 mm","公称直径":"80 mm","中心到端点":"97 mm","角度":"90.00°","尺寸":"80 mmø-80 mmø-80 mmø","图像":"<无>","标记":"24","套管外半径":"50 mm","中心到端点标签":"97 mm","角度 1":"90.00°","IsCustom":"否","K 系数":"0","类型图像":"<无>","成本":"0.00","查找表名称":"M_Tee - PVC - Sch 40"}},{"uuid":"7c12137a-d7a0-4210-b7da-25589395af0a-0003c2a0","name":"","familyName":"三通 - PVC - Sch 40","typeName":"","typeId":-1,"revitId":"246432","type":"Element","category":"OST_PipeFittingCenterLine","properties":{"Category":"中心线","Name":"","ElementPoint":null,"ElementRotation":null,"Mirrored":null,"HandFlipped":null,"HandOrientation":null,"FacingFlipped":null,"FacingOrientation":null,"Translation":null,"matrix":null,"BoundingBox":"(-0.890448615, -1.597019144, 0.547408793),(-1.208198615, -1.597019144, -0.088091207)","记号尺寸":"40 mm","套管外半径":"50 mm","套管外径":"101 mm","公称半径":"40 mm","公称直径":"80 mm","中心到端点标签":"97 mm","中心到端点":"97 mm","角度":"90.00°","角度 1":"90.00°","标高":"发泡顶","主体":"标高 : 发泡顶","偏移":"-170","系统分类":"其他","系统类型":"排水系统","系统名称":"排水系统 3","损失方法":"3bf616f9-6b98-4a21-80ff-da1120c8f6d6","图像":"<无>","总体大小":"80 mmø-80 mmø-80 mmø","隔热层厚度":"0 mm","压降":"0.0 Pa","使用注释比例":"否","尺寸":"80 mmø-80 mmø-80 mmø","IsCustom":"否","标记":"24","创建的阶段":"阶段 1","拆除的阶段":"无"}},{"uuid":"7c12137a-d7a0-4210-b7da-25589395af0a-0003c3ff","name":"标准","familyName":"变径管接头 - PVC - Sch 40","typeName":"标准","typeId":241616,"revitId":"246783","type":"FamilyInstance","category":"OST_PipeFitting","properties":{"Category":"管件","Name":"标准","ElementPoint":"(-0.890448615, -3.239459682, 0.564304626)","ElementRotation":"(0.000000000, 0.000000000, 1.000000000)","Mirrored":"False","HandFlipped":"False","HandOrientation":"(0.000000000, 0.000000000, 1.000000000)","FacingFlipped":"False","FacingOrientation":"(0.000000000, -1.000000000, 0.000000000)","Translation":"(-0.890448615, -3.239459682, 0.564304626)","matrix":"0,0,1,0,0,-1,0,0,1,0,0,0,-0.271408737859289,-0.987387310987004,0.172000049999968,1","BoundingBox":"(-0.720517769, -3.069528836, 0.963972441),(-1.060379461, -3.409390528, 0.564304626)","总体大小":"80 mmø-50 mmø","隔热层厚度":"0 mm","压降":"0.0 Pa","标高":"展示层面","主体":"标高 : 展示层面","偏移":"172","创建的阶段":"阶段 1","拆除的阶段":"无","系统分类":"其他","系统类型":"排水系统","系统名称":"排水系统 3","损失方法":"3bf616f9-6b98-4a21-80ff-da1120c8f6d6","使用注释比例":"否","长度":"93 mm","记号尺寸 2":"28 mm","记号尺寸 1":"41 mm","偏移宽度":"40.0000 mm","偏移高度":"40.0000 mm","公称半径 2":"25 mm","公称直径 2":"50 mm","套管长度 2":"48 mm","套管外径 2":"70 mm","套管外径 1":"104 mm","公称半径 1":"40 mm","公称直径 1":"80 mm","套管长度 1":"71 mm","尺寸":"80 mmø-50 mmø","图像":"<无>","标记":"25","可见性 3":"是","可见性 2":"否","可见性 1":"否","最大公称直径 12":"80 mm","套管外半径 2":"35 mm","套管外半径 1":"52 mm","长度 1":"3048 mm","长度标签":"122 mm","长度 2":"3048 mm","IsCustom":"否","K 系数":"0","类型图像":"<无>","成本":"0.00","查找表名称":"M_Coupling Reducing - PVC - Sch 40"}},{"uuid":"7c12137a-d7a0-4210-b7da-25589395af0a-0003c400","name":"","familyName":"变径管接头 - PVC - Sch 40","typeName":"","typeId":-1,"revitId":"246784","type":"Element","category":"OST_PipeFittingCenterLine","properties":{"Category":"中心线","Name":"","ElementPoint":null,"ElementRotation":null,"Mirrored":null,"HandFlipped":null,"HandOrientation":null,"FacingFlipped":null,"FacingOrientation":null,"Translation":null,"matrix":null,"BoundingBox":"(-0.890448615, -3.239459682, 0.963972441),(-0.890448615, -3.239459682, 0.564304626)","可见性 3":"是","可见性 2":"否","可见性 1":"否","长度":"93 mm","记号尺寸 2":"28 mm","记号尺寸 1":"41 mm","公称半径 2":"25 mm","公称直径 2":"50 mm","最大公称直径 12":"80 mm","套管长度 2":"48 mm","套管外半径 2":"35 mm","套管外半径 1":"52 mm","套管外径 2":"70 mm","套管外径 1":"104 mm","长度 1":"3048 mm","长度标签":"122 mm","公称半径 1":"40 mm","公称直径 1":"80 mm","长度 2":"3048 mm","套管长度 1":"71 mm","标高":"展示层面","主体":"标高 : 展示层面","偏移":"172","系统分类":"其他","系统类型":"排水系统","系统名称":"排水系统 3","损失方法":"3bf616f9-6b98-4a21-80ff-da1120c8f6d6","图像":"<无>","总体大小":"80 mmø-50 mmø","隔热层厚度":"0 mm","压降":"0.0 Pa","使用注释比例":"否","尺寸":"80 mmø-50 mmø","IsCustom":"否","偏移高度":"40.0000 mm","偏移宽度":"40.0000 mm","标记":"25","创建的阶段":"阶段 1","拆除的阶段":"无"}},{"uuid":"f9799bdc-07db-4022-a03b-dc4d0f136148-0003c786","name":"常规 - 10","familyName":"基本墙","typeName":"常规 - 10","typeId":171469,"revitId":"247686","type":"Wall","category":"OST_Walls","properties":{"Category":"墙","Name":"常规 - 10","ElementPoint":null,"ElementRotation":null,"Mirrored":null,"HandFlipped":null,"HandOrientation":null,"FacingFlipped":null,"FacingOrientation":null,"Translation":null,"matrix":null,"BoundingBox":"(-0.446234871, -1.782149536, 3.903024457),(-1.334248869, -1.814957935, 3.634578866)","结构":"否","启用分析模型":"否","结构用途":"非承重","定位线":"面层面: 外部","图像":"<无>","创建的阶段":"阶段 1","拆除的阶段":"无","底部约束":"展示层面","底部偏移":"1108","已附着底部":"否","底部延伸距离":"0","顶部约束":"未连接","无连接高度":"82","顶部偏移":"0","已附着顶部":"否","顶部延伸距离":"0","房间边界":"是","长度":"160","面积":"0 m²","体积":"0.00 m³","与体量相关":"否","在插入点包络":"不包络","在端点包络":"无","厚度":"10","类型图像":"<无>","结构材质":"硬质隔热层","成本":"0.00","功能":"外部","壁厚":"0","幕墙":"否","传热系数(U)":"3.5000 W/(m²·K)","热阻(R)":"0.2857 (m²·K)/W","热质量":"0.03 kJ/K","吸收率":"0.7","粗糙度":"3"}},{"uuid":"f9799bdc-07db-4022-a03b-dc4d0f136148-0003c9aa","name":"600 mm Arial","familyName":"模型文字","typeName":"600 mm Arial","typeId":403,"revitId":"248234","type":"ModelText","category":"OST_GenericModel","properties":{"Category":"常规模型","Name":"600 mm Arial","ElementPoint":"(-1.334248869, -1.814957935, 3.710130471)","ElementRotation":null,"Mirrored":null,"HandFlipped":null,"HandOrientation":null,"FacingFlipped":null,"FacingOrientation":null,"Translation":null,"matrix":null,"BoundingBox":"(-0.446234871, -1.814957935, 3.893857505),(-1.334248869, -1.855968434, 3.687164591)","图像":"<无>","创建的阶段":"阶段 1","拆除的阶段":"无","工作平面":"基本墙 : 常规 - 10","文字":"排水立管","水平对齐":"左","深度":"1","子类别":"常规模型","材质":"蓝色, 实体","类型图像":"<无>","成本":"0.00","文字字体":"Microsoft Sans Serif","文字大小":"50","粗体":"否","斜体":"否"}},{"uuid":"f9799bdc-07db-4022-a03b-dc4d0f136148-0003cb32","name":"常规 - 10","familyName":"基本墙","typeName":"常规 - 10","typeId":171469,"revitId":"248626","type":"Wall","category":"OST_Walls","properties":{"Category":"墙","Name":"常规 - 10","ElementPoint":null,"ElementRotation":null,"Mirrored":null,"HandFlipped":null,"HandOrientation":null,"FacingFlipped":null,"FacingOrientation":null,"Translation":null,"matrix":null,"BoundingBox":"(-2.976152884, 0.373362275, 1.345144357),(-3.669900862, 0.340553876, 1.100774600)","结构":"否","启用分析模型":"否","结构用途":"非承重","定位线":"面层面: 外部","图像":"<无>","创建的阶段":"阶段 1","拆除的阶段":"无","底部约束":"展示层面","底部偏移":"336","已附着底部":"否","底部延伸距离":"0","顶部约束":"未连接","无连接高度":"74","顶部偏移":"0","已附着顶部":"否","顶部延伸距离":"0","房间边界":"是","长度":"154","面积":"0 m²","体积":"0.00 m³","与体量相关":"否","在插入点包络":"不包络","在端点包络":"无","厚度":"10","类型图像":"<无>","结构材质":"硬质隔热层","成本":"0.00","功能":"外部","壁厚":"0","幕墙":"否","传热系数(U)":"3.5000 W/(m²·K)","热阻(R)":"0.2857 (m²·K)/W","热质量":"0.03 kJ/K","吸收率":"0.7","粗糙度":"3"}},{"uuid":"f9799bdc-07db-4022-a03b-dc4d0f136148-0003cb3f","name":"600 mm Arial","familyName":"模型文字","typeName":"600 mm Arial","typeId":403,"revitId":"248639","type":"ModelText","category":"OST_GenericModel","properties":{"Category":"常规模型","Name":"600 mm Arial","ElementPoint":"(-3.633755242, 0.340553876, 1.139746440)","ElementRotation":null,"Mirrored":null,"HandFlipped":null,"HandOrientation":null,"FacingFlipped":null,"FacingOrientation":null,"Translation":null,"matrix":null,"BoundingBox":"(-3.189748243, 0.340553876, 1.320921710),(-3.633755242, 0.299543377, 1.119332326)","图像":"<无>","创建的阶段":"阶段 1","拆除的阶段":"无","工作平面":"基本墙 : 常规 - 10","文字":"地漏","水平对齐":"左","深度":"1","子类别":"常规模型","材质":"蓝色, 实体","类型图像":"<无>","成本":"0.00","文字字体":"Microsoft Sans Serif","文字大小":"50","粗体":"否","斜体":"否"}},{"uuid":"f9799bdc-07db-4022-a03b-dc4d0f136148-0003d0de","name":"常规 - 10","familyName":"基本墙","typeName":"常规 - 10","typeId":171469,"revitId":"250078","type":"Wall","category":"OST_Walls","properties":{"Category":"墙","Name":"常规 - 10","ElementPoint":null,"ElementRotation":null,"Mirrored":null,"HandFlipped":null,"HandOrientation":null,"FacingFlipped":null,"FacingOrientation":null,"Translation":null,"matrix":null,"BoundingBox":"(-0.435723945, -3.416007804, 1.345144357),(-1.359883564, -3.448816203, 1.100774600)","结构":"否","启用分析模型":"否","结构用途":"非承重","定位线":"面层面: 外部","图像":"<无>","创建的阶段":"阶段 1","拆除的阶段":"无","底部约束":"展示层面","底部偏移":"336","已附着底部":"否","底部延伸距离":"0","顶部约束":"未连接","无连接高度":"74","顶部偏移":"0","已附着顶部":"否","顶部延伸距离":"0","房间边界":"是","长度":"154","面积":"0 m²","体积":"0.00 m³","与体量相关":"否","在插入点包络":"不包络","在端点包络":"无","厚度":"10","类型图像":"<无>","结构材质":"硬质隔热层","成本":"0.00","功能":"外部","壁厚":"0","幕墙":"否","传热系数(U)":"3.5000 W/(m²·K)","热阻(R)":"0.2857 (m²·K)/W","热质量":"0.03 kJ/K","吸收率":"0.7","粗糙度":"3"}},{"uuid":"f9799bdc-07db-4022-a03b-dc4d0f136148-0003d0eb","name":"600 mm Arial","familyName":"模型文字","typeName":"600 mm Arial","typeId":403,"revitId":"250091","type":"ModelText","category":"OST_GenericModel","properties":{"Category":"常规模型","Name":"600 mm Arial","ElementPoint":"(-1.323737943, -3.448816203, 1.139746440)","ElementRotation":null,"Mirrored":null,"HandFlipped":null,"HandOrientation":null,"FacingFlipped":null,"FacingOrientation":null,"Translation":null,"matrix":null,"BoundingBox":"(-0.435723945, -3.448816203, 1.323473475),(-1.323737943, -3.489826702, 1.116780561)","图像":"<无>","创建的阶段":"阶段 1","拆除的阶段":"无","工作平面":"基本墙 : 常规 - 10","文字":"管根防水","水平对齐":"左","深度":"1","子类别":"常规模型","材质":"蓝色, 实体","类型图像":"<无>","成本":"0.00","文字字体":"Microsoft Sans Serif","文字大小":"50","粗体":"否","斜体":"否"}},{"uuid":"f9799bdc-07db-4022-a03b-dc4d0f136148-0003d196","name":"常规 - 10","familyName":"基本墙","typeName":"常规 - 10","typeId":171469,"revitId":"250262","type":"Wall","category":"OST_Walls","properties":{"Category":"墙","Name":"常规 - 10","ElementPoint":null,"ElementRotation":null,"Mirrored":null,"HandFlipped":null,"HandOrientation":null,"FacingFlipped":null,"FacingOrientation":null,"Translation":null,"matrix":null,"BoundingBox":"(-2.464889664, -3.318499786, 1.345144357),(-3.389049283, -3.351308185, 1.100774600)","结构":"否","启用分析模型":"否","结构用途":"非承重","定位线":"面层面: 外部","图像":"<无>","创建的阶段":"阶段 1","拆除的阶段":"无","底部约束":"展示层面","底部偏移":"336","已附着底部":"否","底部延伸距离":"0","顶部约束":"未连接","无连接高度":"74","顶部偏移":"0","已附着顶部":"否","顶部延伸距离":"0","房间边界":"是","长度":"154","面积":"0 m²","体积":"0.00 m³","与体量相关":"否","在插入点包络":"不包络","在端点包络":"无","厚度":"10","类型图像":"<无>","结构材质":"硬质隔热层","成本":"0.00","功能":"外部","壁厚":"0","幕墙":"否","传热系数(U)":"3.5000 W/(m²·K)","热阻(R)":"0.2857 (m²·K)/W","热质量":"0.03 kJ/K","吸收率":"0.7","粗糙度":"3"}},{"uuid":"f9799bdc-07db-4022-a03b-dc4d0f136148-0003d1a3","name":"600 mm Arial","familyName":"模型文字","typeName":"600 mm Arial","typeId":403,"revitId":"250275","type":"ModelText","category":"OST_GenericModel","properties":{"Category":"常规模型","Name":"600 mm Arial","ElementPoint":"(-3.352903662, -3.351308185, 1.139746440)","ElementRotation":null,"Mirrored":null,"HandFlipped":null,"HandOrientation":null,"FacingFlipped":null,"FacingOrientation":null,"Translation":null,"matrix":null,"BoundingBox":"(-2.464889664, -3.351308185, 1.323473475),(-3.352903662, -3.392318684, 1.116780561)","图像":"<无>","创建的阶段":"阶段 1","拆除的阶段":"无","工作平面":"基本墙 : 常规 - 10","文字":"水泥砂浆","水平对齐":"左","深度":"1","子类别":"常规模型","材质":"蓝色, 实体","类型图像":"<无>","成本":"0.00","文字字体":"Microsoft Sans Serif","文字大小":"50","粗体":"否","斜体":"否"}},{"uuid":"f9799bdc-07db-4022-a03b-dc4d0f136148-0003d1c5","name":"常规 - 10","familyName":"基本墙","typeName":"常规 - 10","typeId":171469,"revitId":"250309","type":"Wall","category":"OST_Walls","properties":{"Category":"墙","Name":"常规 - 10","ElementPoint":null,"ElementRotation":null,"Mirrored":null,"HandFlipped":null,"HandOrientation":null,"FacingFlipped":null,"FacingOrientation":null,"Translation":null,"matrix":null,"BoundingBox":"(-2.949334284, -3.679392175, 1.195813326),(-4.065155329, -3.712200573, 0.951443570)","结构":"否","启用分析模型":"否","结构用途":"非承重","定位线":"面层面: 外部","图像":"<无>","创建的阶段":"阶段 1","拆除的阶段":"无","底部约束":"展示层面","底部偏移":"290","已附着底部":"否","底部延伸距离":"0","顶部约束":"未连接","无连接高度":"74","顶部偏移":"0","已附着顶部":"否","顶部延伸距离":"0","房间边界":"是","长度":"154","面积":"0 m²","体积":"0.00 m³","与体量相关":"否","在插入点包络":"不包络","在端点包络":"无","厚度":"10","类型图像":"<无>","结构材质":"硬质隔热层","成本":"0.00","功能":"外部","壁厚":"0","幕墙":"否","传热系数(U)":"3.5000 W/(m²·K)","热阻(R)":"0.2857 (m²·K)/W","热质量":"0.03 kJ/K","吸收率":"0.7","粗糙度":"3"}},{"uuid":"f9799bdc-07db-4022-a03b-dc4d0f136148-0003d1d2","name":"600 mm Arial","familyName":"模型文字","typeName":"600 mm Arial","typeId":403,"revitId":"250322","type":"ModelText","category":"OST_GenericModel","properties":{"Category":"常规模型","Name":"600 mm Arial","ElementPoint":"(-4.022796163, -3.712200573, 1.005076188)","ElementRotation":null,"Mirrored":null,"HandFlipped":null,"HandOrientation":null,"FacingFlipped":null,"FacingOrientation":null,"Translation":null,"matrix":null,"BoundingBox":"(-2.912778665, -3.712200573, 1.188803223),(-4.022796163, -3.753211072, 0.982110309)","图像":"<无>","创建的阶段":"阶段 1","拆除的阶段":"无","工作平面":"基本墙 : 常规 - 10","文字":"聚氨酯防水","水平对齐":"左","深度":"1","子类别":"常规模型","材质":"蓝色, 实体","类型图像":"<无>","成本":"0.00","文字字体":"Microsoft Sans Serif","文字大小":"50","粗体":"否","斜体":"否"}},{"uuid":"f9799bdc-07db-4022-a03b-dc4d0f136148-0003d1f2","name":"常规 - 10","familyName":"基本墙","typeName":"常规 - 10","typeId":171469,"revitId":"250354","type":"Wall","category":"OST_Walls","properties":{"Category":"墙","Name":"常规 - 10","ElementPoint":null,"ElementRotation":null,"Mirrored":null,"HandFlipped":null,"HandOrientation":null,"FacingFlipped":null,"FacingOrientation":null,"Translation":null,"matrix":null,"BoundingBox":"(-3.371407351, -4.105901361, 1.064579730),(-4.586062430, -4.138709760, 0.820209974)","结构":"否","启用分析模型":"否","结构用途":"非承重","定位线":"面层面: 外部","图像":"<无>","创建的阶段":"阶段 1","拆除的阶段":"无","底部约束":"展示层面","底部偏移":"250","已附着底部":"否","底部延伸距离":"0","顶部约束":"未连接","无连接高度":"74","顶部偏移":"0","已附着顶部":"否","顶部延伸距离":"0","房间边界":"是","长度":"154","面积":"0 m²","体积":"0.00 m³","与体量相关":"否","在插入点包络":"不包络","在端点包络":"无","厚度":"10","类型图像":"<无>","结构材质":"硬质隔热层","成本":"0.00","功能":"外部","壁厚":"0","幕墙":"否","传热系数(U)":"3.5000 W/(m²·K)","热阻(R)":"0.2857 (m²·K)/W","热质量":"0.03 kJ/K","吸收率":"0.7","粗糙度":"3"}},{"uuid":"f9799bdc-07db-4022-a03b-dc4d0f136148-0003d1ff","name":"600 mm Arial","familyName":"模型文字","typeName":"600 mm Arial","typeId":403,"revitId":"250367","type":"ModelText","category":"OST_GenericModel","properties":{"Category":"常规模型","Name":"600 mm Arial","ElementPoint":"(-4.548132255, -4.138709760, 0.868019780)","ElementRotation":null,"Mirrored":null,"HandFlipped":null,"HandOrientation":null,"FacingFlipped":null,"FacingOrientation":null,"Translation":null,"matrix":null,"BoundingBox":"(-3.438114757, -4.138709760, 1.051746814),(-4.548132255, -4.179720259, 0.845053900)","图像":"<无>","创建的阶段":"阶段 1","拆除的阶段":"无","工作平面":"基本墙 : 常规 - 10","文字":"发泡混凝土","水平对齐":"左","深度":"1","子类别":"常规模型","材质":"蓝色, 实体","类型图像":"<无>","成本":"0.00","文字字体":"Microsoft Sans Serif","文字大小":"50","粗体":"否","斜体":"否"}}]}}