{"objects":{"components":[{"uuid":"932c53f7-e21f-442d-91c5-dde3052a819c-00017831","name":"","familyName":"","typeName":"","typeId":-1,"revitId":"96305","type":"BasePoint","category":"OST_ProjectBasePoint","properties":{"Category":"项目基点","Name":"","ElementPoint":null,"ElementRotation":null,"Mirrored":null,"Translation":null,"matrix":null,"BoundingBox":"(0.000000000, -0.026246719, 0.000000000),(0.000000000, -0.026246719, 0.000000000)","北/南":"3277949679.000","东/西":"487318296.000","高程":"236906.000","到正北的角度":"301.79°"}}]}}